{
	"name": "helloAzurefunctionCall",
	"properties": {
		"activities": [
			{
				"name": "helloword",
				"description": "fuzzy join: atc 2020 2021 and  atc affectation",
				"type": "AzureFunctionActivity",
				"dependsOn": [],
				"policy": {
					"timeout": "7.00:00:00",
					"retry": 0,
					"retryIntervalInSeconds": 30,
					"secureOutput": false,
					"secureInput": false
				},
				"userProperties": [],
				"typeProperties": {
					"functionName": "HelloWord",
					"method": "POST",
					"body": {
						"name": "bobl"
					}
				},
				"linkedServiceName": {
					"referenceName": "data transformation azure function",
					"type": "LinkedServiceReference"
				}
			},
			{
				"name": "importDataDSC",
				"description": "import all file un folder",
				"type": "AzureFunctionActivity",
				"dependsOn": [],
				"policy": {
					"timeout": "7.00:00:00",
					"retry": 0,
					"retryIntervalInSeconds": 30,
					"secureOutput": false,
					"secureInput": false
				},
				"userProperties": [],
				"typeProperties": {
					"functionName": "AF_IMPORT_ECOUL_DSC",
					"method": "POST",
					"body": {
						"inputContainer": "data-input",
						"inputFolderPath": "Ecoulement/DSC",
						"outputContainer": "data-warehouse",
						"outputpath": "Temp/DSC_ECOULEMENT.csv"
					}
				},
				"linkedServiceName": {
					"referenceName": "data transformation azure function",
					"type": "LinkedServiceReference"
				}
			},
			{
				"name": "importDataTereva",
				"description": "import all file un folder",
				"type": "AzureFunctionActivity",
				"dependsOn": [],
				"policy": {
					"timeout": "7.00:00:00",
					"retry": 0,
					"retryIntervalInSeconds": 30,
					"secureOutput": false,
					"secureInput": false
				},
				"userProperties": [],
				"typeProperties": {
					"functionName": "AF_IMPORT_ECOUL_TEREVA",
					"method": "POST",
					"body": {
						"inputcontainer": "data-input",
						"folderpath": "Ecoulement/Téréva",
						"outputcontainer": "data-warehouse",
						"outputpath": "Temp/TEREVA_ECOULEMENT.xlsx"
					}
				},
				"linkedServiceName": {
					"referenceName": "data transformation azure function",
					"type": "LinkedServiceReference"
				}
			},
			{
				"name": "VFimport",
				"description": "import all file un folder",
				"type": "AzureFunctionActivity",
				"dependsOn": [],
				"policy": {
					"timeout": "7.00:00:00",
					"retry": 0,
					"retryIntervalInSeconds": 30,
					"secureOutput": false,
					"secureInput": false
				},
				"userProperties": [],
				"typeProperties": {
					"functionName": "AF_IMPORT_ECOUL_VFCONFORT",
					"method": "POST",
					"body": {
						"inputcontainer": "data-input",
						"folderpath": "Ecoulement/VF Confort",
						"outputcontainer": "data-warehouse",
						"outputpath": "Temp/CONFORT_ECOULEMENT.xlsx"
					}
				},
				"linkedServiceName": {
					"referenceName": "data transformation azure function",
					"type": "LinkedServiceReference"
				}
			},
			{
				"name": "DATA IMPORTpartedis",
				"type": "AzureFunctionActivity",
				"dependsOn": [],
				"policy": {
					"timeout": "7.00:00:00",
					"retry": 0,
					"retryIntervalInSeconds": 30,
					"secureOutput": false,
					"secureInput": false
				},
				"userProperties": [],
				"typeProperties": {
					"functionName": "AF_IMPORT_ECOUL_PARTEDIS",
					"method": "POST",
					"body": {
						"inputcontainer": "data-input",
						"folderpath": "Ecoulement/Partedis",
						"outputcontainer": "data-warehouse",
						"outputpath": "Temp/PARTEDIS_ECOULEMENT.xlsx"
					}
				},
				"linkedServiceName": {
					"referenceName": "data transformation azure function",
					"type": "LinkedServiceReference"
				}
			}
		],
		"folder": {
			"name": "tutoriel&test"
		},
		"annotations": [],
		"lastPublishTime": "2021-09-06T17:37:12Z"
	},
	"type": "Microsoft.DataFactory/factories/pipelines"
}